flake8_sfs.py
flake8_sfs-1.0.1.dist-info/licenses/LICENSE.rst
flake8_sfs-1.0.1.dist-info/METADATA
flake8_sfs-1.0.1.dist-info/WHEEL
flake8_sfs-1.0.1.dist-info/entry_points.txt
flake8_sfs-1.0.1.dist-info/top_level.txt
flake8_sfs-1.0.1.dist-info/zip-safe
flake8_sfs-1.0.1.dist-info/RECORD
