Metadata-Version: 2.4
Name: flake8-sfs
Version: 1.0.1
Summary: Python String Formatting Style (SFS) plugin for flake8
Author: Peter J. A. Cock
Maintainer-email: "Peter J. A. Cock" <p.j.a.cock@googlemail.com>
License: MIT
Project-URL: Homepage, https://github.com/peterjc/flake8-sfs
Project-URL: Source Code, https://github.com/peterjc/flake8-sfs/
Project-URL: Bug Tracker, https://github.com/peterjc/flake8-sfs/issues
Project-URL: Documentation, https://github.com/peterjc/flake8-sfs/blob/master/README.rst
Keywords: strings,formatting,style,f-string
Classifier: Development Status :: 4 - Beta
Classifier: Intended Audience :: Developers
Classifier: Framework :: Flake8
Classifier: License :: OSI Approved :: MIT License
Classifier: Operating System :: OS Independent
Classifier: Programming Language :: Python
Classifier: Topic :: Software Development :: Libraries :: Python Modules
Classifier: Topic :: Software Development :: Quality Assurance
Classifier: Programming Language :: Python :: 3
Classifier: Programming Language :: Python :: 3 :: Only
Requires-Python: >=3.9
License-File: LICENSE.rst
Requires-Dist: flake8>=3
Provides-Extra: develop
Requires-Dist: build; extra == "develop"
Requires-Dist: twine; extra == "develop"
Dynamic: license-file
